carsxe-1.1.2.dist-info/licenses/LICENSE
carsxe_api/__init__.py
carsxe_api/index.py
carsxe_api/types.py
carsxe-1.1.2.dist-info/METADATA
carsxe-1.1.2.dist-info/WHEEL
carsxe-1.1.2.dist-info/top_level.txt
carsxe-1.1.2.dist-info/RECORD
