Metadata-Version: 2.4
Name: carsxe
Version: 1.1.2
Summary: A powerful, easy-to-use API for vehicle data including specs, market value, license plate decoding, and more.
Author: CarsXE
Author-email: CarsXE <developer@carsxe.com>
License: MIT License
Classifier: Programming Language :: Python :: 3
Classifier: License :: OSI Approved :: MIT License
Classifier: Operating System :: OS Independent
Requires-Python: >=3.7
License-File: LICENSE
Requires-Dist: requests>=2.0.0
Dynamic: author
Dynamic: license-file
Dynamic: requires-python
